setup.py
django_importer/__init__.py
django_importer/utils.py
django_importer.egg-info/PKG-INFO
django_importer.egg-info/SOURCES.txt
django_importer.egg-info/dependency_links.txt
django_importer.egg-info/top_level.txt
django_importer/importers/__init__.py
django_importer/importers/base.py
django_importer/importers/csv_importer.py
django_importer/importers/xml_importer.py