Metadata-Version: 1.0
Name: django-importer
Version: 0.5
Summary: Data importers for Django models
Home-page: http://github.com/ricobl/django-importer/
Author: Enrico Batista da Luz
Author-email: rico.bl@gmail.com
License: UNKNOWN
Platform: UNKNOWN
